seatools/ioc/starters/__init__.py
seatools/ioc/starters/django/__init__.py
seatools/ioc/starters/django/django.py
seatools_starter_django-1.0.2.dist-info/LICENSE
seatools_starter_django-1.0.2.dist-info/METADATA
seatools_starter_django-1.0.2.dist-info/WHEEL
seatools_starter_django-1.0.2.dist-info/top_level.txt
seatools_starter_django-1.0.2.dist-info/RECORD
